[
  {
    "date":1779753600000,
    "book":"long",
    "ticker":"US.ALAB",
    "shares":293.8868391184,
    "weight":0.1153460115,
    "gross_market_value":93667.6133638307,
    "net_market_value":93667.6133638307,
    "name":"Astera Labs",
    "industry_labels":"半导体",
    "market_value":null
  },
  {
    "date":1779753600000,
    "book":"long",
    "ticker":"US.CRWD",
    "shares":124.4345670069,
    "weight":0.1029040627,
    "gross_market_value":83564.0334735074,
    "net_market_value":83564.0334735074,
    "name":"CrowdStrike",
    "industry_labels":"软件基础设施",
    "market_value":null
  },
  {
    "date":1779753600000,
    "book":"long",
    "ticker":"US.QCOM",
    "shares":335.699734425,
    "weight":0.1028606846,
    "gross_market_value":83528.8079196372,
    "net_market_value":83528.8079196372,
    "name":"高通",
    "industry_labels":"半导体",
    "market_value":null
  },
  {
    "date":1779753600000,
    "book":"long",
    "ticker":"US.NOK",
    "shares":5053.656133341,
    "weight":0.1024350646,
    "gross_market_value":83183.1799547926,
    "net_market_value":83183.1799547926,
    "name":"诺基亚",
    "industry_labels":"通讯设备",
    "market_value":null
  },
  {
    "date":1779753600000,
    "book":"long",
    "ticker":"US.RKLB",
    "shares":569.1611669804,
    "weight":0.100367107,
    "gross_market_value":81503.8791115939,
    "net_market_value":81503.8791115939,
    "name":"Rocket Lab",
    "industry_labels":"航空航天与国防",
    "market_value":null
  },
  {
    "date":1779753600000,
    "book":"long",
    "ticker":"US.PANW",
    "shares":313.002911152,
    "weight":0.0989627958,
    "gross_market_value":80363.4974382864,
    "net_market_value":80363.4974382864,
    "name":"Palo Alto Networks",
    "industry_labels":"软件基础设施",
    "market_value":null
  },
  {
    "date":1779753600000,
    "book":"long",
    "ticker":"US.IONQ",
    "shares":1256.7334614638,
    "weight":0.0984577644,
    "gross_market_value":79953.3828183269,
    "net_market_value":79953.3828183269,
    "name":"IonQ Inc",
    "industry_labels":"计算机硬件",
    "market_value":null
  },
  {
    "date":1779753600000,
    "book":"long",
    "ticker":"US.RGTI",
    "shares":3106.8035975441,
    "weight":0.0958947067,
    "gross_market_value":77872.0321724431,
    "net_market_value":77872.0321724431,
    "name":"Rigetti Computing",
    "industry_labels":"计算机硬件",
    "market_value":null
  },
  {
    "date":1779753600000,
    "book":"long",
    "ticker":"US.QBTS",
    "shares":2753.252523752,
    "weight":0.0943227162,
    "gross_market_value":76595.4852107817,
    "net_market_value":76595.4852107817,
    "name":"D-Wave Quantum",
    "industry_labels":"计算机硬件",
    "market_value":null
  },
  {
    "date":1779753600000,
    "book":"long",
    "ticker":"US.NBIS",
    "shares":345.2165675635,
    "weight":0.0884490864,
    "gross_market_value":71825.7590472557,
    "net_market_value":71825.7590472557,
    "name":"NEBIUS",
    "industry_labels":"互联网内容与信息",
    "market_value":null
  }
]