[
  {
    "ticker":"US.EWT",
    "buy_count":4,
    "total_buy_value":215741.6313512542,
    "first_signal_date":1767139200000,
    "last_signal_date":1775779200000,
    "first_trade_date":1767312000000,
    "last_trade_date":1776038400000,
    "name":"安硕MSCI台湾ETF",
    "industry_labels":null,
    "latest_adj_close":93.77
  },
  {
    "ticker":"US.SMH",
    "buy_count":4,
    "total_buy_value":209319.7779991788,
    "first_signal_date":1767139200000,
    "last_signal_date":1775088000000,
    "first_trade_date":1767312000000,
    "last_trade_date":1775433600000,
    "name":"半导体指数ETF-VanEck",
    "industry_labels":null,
    "latest_adj_close":561.25
  },
  {
    "ticker":"US.EWY",
    "buy_count":3,
    "total_buy_value":159641.2327766636,
    "first_signal_date":1767139200000,
    "last_signal_date":1775779200000,
    "first_trade_date":1767312000000,
    "last_trade_date":1776038400000,
    "name":"韩国ETF-iShares MSCI",
    "industry_labels":null,
    "latest_adj_close":178.5
  },
  {
    "ticker":"US.ETHA",
    "buy_count":3,
    "total_buy_value":158523.0342405271,
    "first_signal_date":1767657600000,
    "last_signal_date":1775779200000,
    "first_trade_date":1767744000000,
    "last_trade_date":1776038400000,
    "name":"以太坊ETF-iShares",
    "industry_labels":null,
    "latest_adj_close":17.24
  },
  {
    "ticker":"US.SOXX",
    "buy_count":3,
    "total_buy_value":155331.3954821397,
    "first_signal_date":1767139200000,
    "last_signal_date":1775088000000,
    "first_trade_date":1767312000000,
    "last_trade_date":1775433600000,
    "name":"半导体ETF-iShares",
    "industry_labels":null,
    "latest_adj_close":515.99
  },
  {
    "ticker":"US.IGV",
    "buy_count":2,
    "total_buy_value":114513.0742480951,
    "first_signal_date":1772668800000,
    "last_signal_date":1778198400000,
    "first_trade_date":1772755200000,
    "last_trade_date":1778457600000,
    "name":"扩展科技软件行业ETF-iShares",
    "industry_labels":null,
    "latest_adj_close":89.44
  },
  {
    "ticker":"US.GLD",
    "buy_count":2,
    "total_buy_value":110268.0364571258,
    "first_signal_date":1769558400000,
    "last_signal_date":1770768000000,
    "first_trade_date":1769644800000,
    "last_trade_date":1770854400000,
    "name":"黄金ETF-SPDR",
    "industry_labels":null,
    "latest_adj_close":432.93
  },
  {
    "ticker":"US.ARKK",
    "buy_count":2,
    "total_buy_value":109068.1384905383,
    "first_signal_date":1772668800000,
    "last_signal_date":1776384000000,
    "first_trade_date":1772755200000,
    "last_trade_date":1776643200000,
    "name":"创新ETF-ARK",
    "industry_labels":null,
    "latest_adj_close":78.21
  },
  {
    "ticker":"US.VGT",
    "buy_count":2,
    "total_buy_value":109068.1384905383,
    "first_signal_date":1772668800000,
    "last_signal_date":1776384000000,
    "first_trade_date":1772755200000,
    "last_trade_date":1776643200000,
    "name":"资讯科技ETF-Vanguard",
    "industry_labels":null,
    "latest_adj_close":112.3
  },
  {
    "ticker":"US.XLK",
    "buy_count":2,
    "total_buy_value":109064.1384905383,
    "first_signal_date":1772668800000,
    "last_signal_date":1776384000000,
    "first_trade_date":1772755200000,
    "last_trade_date":1776643200000,
    "name":"科技行业精选指数ETF-SPDR",
    "industry_labels":null,
    "latest_adj_close":175.2
  },
  {
    "ticker":"US.SPMO",
    "buy_count":2,
    "total_buy_value":108959.1028396528,
    "first_signal_date":1772668800000,
    "last_signal_date":1776988800000,
    "first_trade_date":1772755200000,
    "last_trade_date":1777248000000,
    "name":"Invesco S&P 500 Momentum ETF",
    "industry_labels":null,
    "latest_adj_close":144.45
  },
  {
    "ticker":"US.EWZ",
    "buy_count":2,
    "total_buy_value":108672.8946339518,
    "first_signal_date":1769558400000,
    "last_signal_date":1775088000000,
    "first_trade_date":1769644800000,
    "last_trade_date":1775433600000,
    "name":"巴西ETF-iShares",
    "industry_labels":null,
    "latest_adj_close":38.24
  },
  {
    "ticker":"US.EFA",
    "buy_count":2,
    "total_buy_value":108451.9162274799,
    "first_signal_date":1772064000000,
    "last_signal_date":1775088000000,
    "first_trade_date":1772150400000,
    "last_trade_date":1775433600000,
    "name":"欧澳远东指数ETF-iShares",
    "industry_labels":null,
    "latest_adj_close":103.14
  },
  {
    "ticker":"US.KRE",
    "buy_count":2,
    "total_buy_value":108431.6504032521,
    "first_signal_date":1770163200000,
    "last_signal_date":1775779200000,
    "first_trade_date":1770249600000,
    "last_trade_date":1776038400000,
    "name":"区域银行指数ETF-SPDR KBW",
    "industry_labels":null,
    "latest_adj_close":68.23
  },
  {
    "ticker":"US.URA",
    "buy_count":2,
    "total_buy_value":108361.0215963912,
    "first_signal_date":1767657600000,
    "last_signal_date":1776384000000,
    "first_trade_date":1767744000000,
    "last_trade_date":1776643200000,
    "name":"铀价ETF-Global X",
    "industry_labels":null,
    "latest_adj_close":54.35
  },
  {
    "ticker":"US.XLU",
    "buy_count":2,
    "total_buy_value":107656.5059387267,
    "first_signal_date":1772064000000,
    "last_signal_date":1773273600000,
    "first_trade_date":1772150400000,
    "last_trade_date":1773360000000,
    "name":"公用事业精选行业指数ETF-SPDR",
    "industry_labels":null,
    "latest_adj_close":45.19
  },
  {
    "ticker":"US.EWJ",
    "buy_count":2,
    "total_buy_value":106303.1771289525,
    "first_signal_date":1770768000000,
    "last_signal_date":1775088000000,
    "first_trade_date":1770854400000,
    "last_trade_date":1775433600000,
    "name":"日本ETF-iShares",
    "industry_labels":null,
    "latest_adj_close":92.06
  },
  {
    "ticker":"US.EEM",
    "buy_count":2,
    "total_buy_value":106100.3985745906,
    "first_signal_date":1767139200000,
    "last_signal_date":1772064000000,
    "first_trade_date":1767312000000,
    "last_trade_date":1772150400000,
    "name":"新兴市场ETF-iShares",
    "industry_labels":null,
    "latest_adj_close":65.82
  },
  {
    "ticker":"US.SPDW",
    "buy_count":2,
    "total_buy_value":106100.3985745906,
    "first_signal_date":1767139200000,
    "last_signal_date":1772064000000,
    "first_trade_date":1767312000000,
    "last_trade_date":1772150400000,
    "name":"SPDR投资组合发达世界(美国除外)ETF",
    "industry_labels":null,
    "latest_adj_close":49.8
  },
  {
    "ticker":"US.VEA",
    "buy_count":2,
    "total_buy_value":106100.3985745906,
    "first_signal_date":1767139200000,
    "last_signal_date":1772064000000,
    "first_trade_date":1767312000000,
    "last_trade_date":1772150400000,
    "name":"富时成熟市场ETF-Vanguard",
    "industry_labels":null,
    "latest_adj_close":69.97
  },
  {
    "ticker":"US.VXUS",
    "buy_count":2,
    "total_buy_value":106090.3985745906,
    "first_signal_date":1767139200000,
    "last_signal_date":1772064000000,
    "first_trade_date":1767312000000,
    "last_trade_date":1772150400000,
    "name":"全世界股票ETF-Vanguard",
    "industry_labels":null,
    "latest_adj_close":84.23
  },
  {
    "ticker":"US.USO",
    "buy_count":2,
    "total_buy_value":105964.852986977,
    "first_signal_date":1771459200000,
    "last_signal_date":1772668800000,
    "first_trade_date":1771545600000,
    "last_trade_date":1772755200000,
    "name":"美国原油ETF",
    "industry_labels":null,
    "latest_adj_close":144.3
  },
  {
    "ticker":"US.GDXJ",
    "buy_count":2,
    "total_buy_value":105223.013051854,
    "first_signal_date":1767657600000,
    "last_signal_date":1770768000000,
    "first_trade_date":1767744000000,
    "last_trade_date":1770854400000,
    "name":"小型黄金矿业ETF-VanEck",
    "industry_labels":null,
    "latest_adj_close":129.87
  },
  {
    "ticker":"US.FTXN",
    "buy_count":2,
    "total_buy_value":104725.5475725897,
    "first_signal_date":1770163200000,
    "last_signal_date":1772668800000,
    "first_trade_date":1770249600000,
    "last_trade_date":1772755200000,
    "name":"First Trust Exchange-Traded Fund VI First Trust Nasdaq Oil & Gas ETF",
    "industry_labels":null,
    "latest_adj_close":36.3694
  },
  {
    "ticker":"US.XOP",
    "buy_count":2,
    "total_buy_value":104707.5475725895,
    "first_signal_date":1770163200000,
    "last_signal_date":1772668800000,
    "first_trade_date":1770249600000,
    "last_trade_date":1772755200000,
    "name":"标普油气开采指数ETF-SPDR",
    "industry_labels":null,
    "latest_adj_close":169.74
  },
  {
    "ticker":"US.XLE",
    "buy_count":2,
    "total_buy_value":104309.1844667878,
    "first_signal_date":1770163200000,
    "last_signal_date":1773273600000,
    "first_trade_date":1770249600000,
    "last_trade_date":1773360000000,
    "name":"能源指数ETF-SPDR",
    "industry_labels":null,
    "latest_adj_close":57.57
  },
  {
    "ticker":"US.XLB",
    "buy_count":2,
    "total_buy_value":104011.4306784426,
    "first_signal_date":1767657600000,
    "last_signal_date":1770163200000,
    "first_trade_date":1767744000000,
    "last_trade_date":1770249600000,
    "name":"SPDR原物料类ETF",
    "industry_labels":null,
    "latest_adj_close":52.14
  },
  {
    "ticker":"US.FTXL",
    "buy_count":2,
    "total_buy_value":102351.5176528893,
    "first_signal_date":1767139200000,
    "last_signal_date":1775088000000,
    "first_trade_date":1767312000000,
    "last_trade_date":1775433600000,
    "name":"First Trust Exchange-Traded Fund VI First Trust Nasdaq Semiconductor ETF",
    "industry_labels":null,
    "latest_adj_close":239.28
  },
  {
    "ticker":"US.DRAM",
    "buy_count":1,
    "total_buy_value":57194.3804989302,
    "first_signal_date":1777593600000,
    "last_signal_date":1777593600000,
    "first_trade_date":1777852800000,
    "last_trade_date":1777852800000,
    "name":"Roundhill Memory ETF",
    "industry_labels":null,
    "latest_adj_close":51.3
  },
  {
    "ticker":"US.IYW",
    "buy_count":1,
    "total_buy_value":56982.6323697149,
    "first_signal_date":1776988800000,
    "last_signal_date":1776988800000,
    "first_trade_date":1777248000000,
    "last_trade_date":1777248000000,
    "name":"美国科技ETF-iShares",
    "industry_labels":null,
    "latest_adj_close":237.07
  },
  {
    "ticker":"US.IAU",
    "buy_count":1,
    "total_buy_value":56318.3769810625,
    "first_signal_date":1769558400000,
    "last_signal_date":1769558400000,
    "first_trade_date":1769644800000,
    "last_trade_date":1769644800000,
    "name":"黄金信托ETF-iShares",
    "industry_labels":null,
    "latest_adj_close":88.71
  },
  {
    "ticker":"US.KBE",
    "buy_count":1,
    "total_buy_value":55689.5733006003,
    "first_signal_date":1775779200000,
    "last_signal_date":1775779200000,
    "first_trade_date":1776038400000,
    "last_trade_date":1776038400000,
    "name":"银行指数ETF-SPDR KBW",
    "industry_labels":null,
    "latest_adj_close":62.7
  },
  {
    "ticker":"US.IJH",
    "buy_count":1,
    "total_buy_value":53986.3825170391,
    "first_signal_date":1771459200000,
    "last_signal_date":1771459200000,
    "first_trade_date":1771545600000,
    "last_trade_date":1771545600000,
    "name":"标普中型股指数ETF-iShares",
    "industry_labels":null,
    "latest_adj_close":73.33
  },
  {
    "ticker":"US.XLI",
    "buy_count":1,
    "total_buy_value":53982.3825170391,
    "first_signal_date":1771459200000,
    "last_signal_date":1771459200000,
    "first_trade_date":1771545600000,
    "last_trade_date":1771545600000,
    "name":"工业指数ETF-SPDR",
    "industry_labels":null,
    "latest_adj_close":174.35
  },
  {
    "ticker":"US.EFV",
    "buy_count":1,
    "total_buy_value":52747.0771026518,
    "first_signal_date":1770163200000,
    "last_signal_date":1770163200000,
    "first_trade_date":1770249600000,
    "last_trade_date":1770249600000,
    "name":"EAFE价值股ETF-iShares",
    "industry_labels":null,
    "latest_adj_close":78.08
  },
  {
    "ticker":"US.SCHD",
    "buy_count":1,
    "total_buy_value":52747.0771026518,
    "first_signal_date":1770163200000,
    "last_signal_date":1770163200000,
    "first_trade_date":1770249600000,
    "last_trade_date":1770249600000,
    "name":"美国红利股ETF-Schwab",
    "industry_labels":null,
    "latest_adj_close":31.76
  },
  {
    "ticker":"US.XLP",
    "buy_count":1,
    "total_buy_value":52747.0771026518,
    "first_signal_date":1770163200000,
    "last_signal_date":1770163200000,
    "first_trade_date":1770249600000,
    "last_trade_date":1770249600000,
    "name":"日常消费品精选行业指数ETF-SPDR",
    "industry_labels":null,
    "latest_adj_close":84.44
  },
  {
    "ticker":"US.MTUM",
    "buy_count":1,
    "total_buy_value":52351.5176528893,
    "first_signal_date":1775088000000,
    "last_signal_date":1775088000000,
    "first_trade_date":1775433600000,
    "last_trade_date":1775433600000,
    "name":"iShares安硕MSCI美国动量因素",
    "industry_labels":null,
    "latest_adj_close":303.24
  },
  {
    "ticker":"US.IBB",
    "buy_count":1,
    "total_buy_value":52351.5176528893,
    "first_signal_date":1775088000000,
    "last_signal_date":1775088000000,
    "first_trade_date":1775433600000,
    "last_trade_date":1775433600000,
    "name":"生物科技指数ETF-iShares",
    "industry_labels":null,
    "latest_adj_close":172.28
  },
  {
    "ticker":"US.XBI",
    "buy_count":1,
    "total_buy_value":52342.5176528894,
    "first_signal_date":1775088000000,
    "last_signal_date":1775088000000,
    "first_trade_date":1775433600000,
    "last_trade_date":1775433600000,
    "name":"标普生物科技ETF-SPDR",
    "industry_labels":null,
    "latest_adj_close":134.91
  },
  {
    "ticker":"US.VXX",
    "buy_count":1,
    "total_buy_value":51978.4704699379,
    "first_signal_date":1772668800000,
    "last_signal_date":1772668800000,
    "first_trade_date":1772755200000,
    "last_trade_date":1772755200000,
    "name":"标普500短期期货恐慌指数ETN-iPath",
    "industry_labels":null,
    "latest_adj_close":27.78
  },
  {
    "ticker":"US.XLC",
    "buy_count":1,
    "total_buy_value":51978.4704699379,
    "first_signal_date":1772668800000,
    "last_signal_date":1772668800000,
    "first_trade_date":1772755200000,
    "last_trade_date":1772755200000,
    "name":"通讯服务行业精选指数ETF-SPDR",
    "industry_labels":null,
    "latest_adj_close":115.86
  },
  {
    "ticker":"US.BITO",
    "buy_count":1,
    "total_buy_value":51562.107364136,
    "first_signal_date":1773273600000,
    "last_signal_date":1773273600000,
    "first_trade_date":1773360000000,
    "last_trade_date":1773360000000,
    "name":"比特币期货ETF-ProShares",
    "industry_labels":null,
    "latest_adj_close":11.04
  },
  {
    "ticker":"US.IBIT",
    "buy_count":1,
    "total_buy_value":51562.107364136,
    "first_signal_date":1773273600000,
    "last_signal_date":1773273600000,
    "first_trade_date":1773360000000,
    "last_trade_date":1773360000000,
    "name":"比特币ETF-iShares",
    "industry_labels":null,
    "latest_adj_close":45.8
  },
  {
    "ticker":"US.SH",
    "buy_count":1,
    "total_buy_value":51562.107364136,
    "first_signal_date":1773273600000,
    "last_signal_date":1773273600000,
    "first_trade_date":1773360000000,
    "last_trade_date":1773360000000,
    "name":"Proshares做空标普500",
    "industry_labels":null,
    "latest_adj_close":33.59
  },
  {
    "ticker":"US.GDX",
    "buy_count":1,
    "total_buy_value":51271.3535757908,
    "first_signal_date":1767657600000,
    "last_signal_date":1767657600000,
    "first_trade_date":1767744000000,
    "last_trade_date":1767744000000,
    "name":"黄金矿业ETF-VanEck",
    "industry_labels":null,
    "latest_adj_close":97.14
  },
  {
    "ticker":"US.MISL",
    "buy_count":1,
    "total_buy_value":51271.3535757908,
    "first_signal_date":1767657600000,
    "last_signal_date":1767657600000,
    "first_trade_date":1767744000000,
    "last_trade_date":1767744000000,
    "name":"FIRST TRUST INDXX AEROSPACE & DEFENSE ETF",
    "industry_labels":null,
    "latest_adj_close":45.51
  },
  {
    "ticker":"US.COPX",
    "buy_count":1,
    "total_buy_value":51271.3535757908,
    "first_signal_date":1767657600000,
    "last_signal_date":1767657600000,
    "first_trade_date":1767744000000,
    "last_trade_date":1767744000000,
    "name":"铜矿ETF-Global X",
    "industry_labels":null,
    "latest_adj_close":90.77
  },
  {
    "ticker":"US.BIL",
    "buy_count":1,
    "total_buy_value":50236.9725721235,
    "first_signal_date":1773878400000,
    "last_signal_date":1773878400000,
    "first_trade_date":1773964800000,
    "last_trade_date":1773964800000,
    "name":"1-3月美国国债ETF-SPDR",
    "industry_labels":null,
    "latest_adj_close":91.49
  },
  {
    "ticker":"US.BOXX",
    "buy_count":1,
    "total_buy_value":50236.9725721235,
    "first_signal_date":1773878400000,
    "last_signal_date":1773878400000,
    "first_trade_date":1773964800000,
    "last_trade_date":1773964800000,
    "name":"ALPHA ARCHITECT 1-3 MONTH BOX ETF",
    "industry_labels":null,
    "latest_adj_close":116.67
  },
  {
    "ticker":"US.IQMM",
    "buy_count":1,
    "total_buy_value":50236.9725721235,
    "first_signal_date":1773878400000,
    "last_signal_date":1773878400000,
    "first_trade_date":1773964800000,
    "last_trade_date":1773964800000,
    "name":"ProShares GENIUS Money Market ETF",
    "industry_labels":null,
    "latest_adj_close":100.08
  },
  {
    "ticker":"US.SGOV",
    "buy_count":1,
    "total_buy_value":50232.9725721235,
    "first_signal_date":1773878400000,
    "last_signal_date":1773878400000,
    "first_trade_date":1773964800000,
    "last_trade_date":1773964800000,
    "name":"0-3月美国国债ETF-iShares",
    "industry_labels":null,
    "latest_adj_close":100.5
  },
  {
    "ticker":"US.SLV",
    "buy_count":1,
    "total_buy_value":50000.0,
    "first_signal_date":1767139200000,
    "last_signal_date":1767139200000,
    "first_trade_date":1767312000000,
    "last_trade_date":1767312000000,
    "name":"白银ETF-iShares",
    "industry_labels":null,
    "latest_adj_close":78.55
  }
]