[
  {
    "signal_date":1782432000000,
    "ticker":"US.DRAM",
    "er3":0.0446851862,
    "er8":0.0456300876,
    "er20":0.1827318619,
    "adv20":3607514828.461499691,
    "adj_close":71.88,
    "market_cap_used":1000000000000.0,
    "vol20_ann":1.2379886491,
    "up_day_ratio20":0.6,
    "er_consistency_penalty":0.1380466757,
    "er20_vol_score":0.1476038266,
    "book":"long",
    "stage":"top50",
    "rank":8,
    "trade_date":null,
    "spy_ma":688.5438638176,
    "spy_above_ma":true,
    "allow_new_buys":true,
    "market_filter_mode":"configured_price_above_ma",
    "selection_style":"waterfall",
    "spy_vol_ann":0.1718072525,
    "high_vol_regime":false,
    "target_count_cap":5,
    "name":"DRAM",
    "industry_labels":null,
    "spy_adj_close":728.99,
    "spy_ma100":703.6980222563,
    "action":"buy",
    "planned_holding":true,
    "weight":null,
    "market_value":null
  },
  {
    "signal_date":1782432000000,
    "ticker":"US.XBI",
    "er3":0.0630481173,
    "er8":0.1733824337,
    "er20":0.176522524,
    "adv20":1388418922.5009999275,
    "adj_close":155.38,
    "market_cap_used":1000000000000.0,
    "vol20_ann":0.3569351488,
    "up_day_ratio20":0.7,
    "er_consistency_penalty":0.1134744067,
    "er20_vol_score":0.4945506897,
    "book":"long",
    "stage":"top50",
    "rank":1,
    "trade_date":null,
    "spy_ma":688.5438638176,
    "spy_above_ma":true,
    "allow_new_buys":true,
    "market_filter_mode":"configured_price_above_ma",
    "selection_style":"waterfall",
    "spy_vol_ann":0.1718072525,
    "high_vol_regime":false,
    "target_count_cap":5,
    "name":"XBI",
    "industry_labels":null,
    "spy_adj_close":728.99,
    "spy_ma100":703.6980222563,
    "action":"keep",
    "planned_holding":true,
    "weight":0.203588478,
    "market_value":171351.677748992
  },
  {
    "signal_date":1782432000000,
    "ticker":"US.JETS",
    "er3":0.0736078522,
    "er8":0.126813307,
    "er20":0.1760112627,
    "adv20":92534325.1874999851,
    "adj_close":33.28,
    "market_cap_used":1000000000000.0,
    "vol20_ann":0.389800049,
    "up_day_ratio20":0.6,
    "er_consistency_penalty":0.1024034105,
    "er20_vol_score":0.4515424335,
    "book":"long",
    "stage":"top50",
    "rank":2,
    "trade_date":null,
    "spy_ma":688.5438638176,
    "spy_above_ma":true,
    "allow_new_buys":true,
    "market_filter_mode":"configured_price_above_ma",
    "selection_style":"waterfall",
    "spy_vol_ann":0.1718072525,
    "high_vol_regime":false,
    "target_count_cap":5,
    "name":"JETS",
    "industry_labels":null,
    "spy_adj_close":728.99,
    "spy_ma100":703.6980222563,
    "action":"keep",
    "planned_holding":true,
    "weight":0.2003177907,
    "market_value":168598.8807435556
  },
  {
    "signal_date":1782432000000,
    "ticker":"US.IBB",
    "er3":0.0583093194,
    "er8":0.1224596263,
    "er20":0.1217229972,
    "adv20":269576155.5170000196,
    "adj_close":187.36,
    "market_cap_used":1000000000000.0,
    "vol20_ann":0.2590740167,
    "up_day_ratio20":0.65,
    "er_consistency_penalty":0.0648869359,
    "er20_vol_score":0.4698386924,
    "book":"long",
    "stage":"top50",
    "rank":3,
    "trade_date":null,
    "spy_ma":688.5438638176,
    "spy_above_ma":true,
    "allow_new_buys":true,
    "market_filter_mode":"configured_price_above_ma",
    "selection_style":"waterfall",
    "spy_vol_ann":0.1718072525,
    "high_vol_regime":false,
    "target_count_cap":5,
    "name":"IBB",
    "industry_labels":null,
    "spy_adj_close":728.99,
    "spy_ma100":703.6980222563,
    "action":"keep",
    "planned_holding":true,
    "weight":0.2019668754,
    "market_value":169986.844504688
  },
  {
    "signal_date":1782432000000,
    "ticker":"US.KRE",
    "er3":0.0342930913,
    "er8":0.0749361825,
    "er20":0.1147436866,
    "adv20":1151671683.992000103,
    "adj_close":75.17,
    "market_cap_used":1000000000000.0,
    "vol20_ann":0.2190375444,
    "up_day_ratio20":0.8,
    "er_consistency_penalty":0.0804505953,
    "er20_vol_score":0.5238539671,
    "book":"long",
    "stage":"top50",
    "rank":5,
    "trade_date":null,
    "spy_ma":688.5438638176,
    "spy_above_ma":true,
    "allow_new_buys":true,
    "market_filter_mode":"configured_price_above_ma",
    "selection_style":"waterfall",
    "spy_vol_ann":0.1718072525,
    "high_vol_regime":false,
    "target_count_cap":5,
    "name":"KRE",
    "industry_labels":null,
    "spy_adj_close":728.99,
    "spy_ma100":703.6980222563,
    "action":"keep",
    "planned_holding":true,
    "weight":0.1987590408,
    "market_value":167286.9478804326
  }
]