[
  {
    "date":1780963200000,
    "book":"long",
    "ticker":"US.GE",
    "shares":818.2339952841,
    "weight":0.2047175949,
    "gross_market_value":270377.2414016919,
    "net_market_value":270377.2414016919,
    "name":"GE航天航空",
    "industry_labels":"航空航天与国防",
    "market_value":270377.2414016919
  },
  {
    "date":1780963200000,
    "book":"long",
    "ticker":"US.ASML",
    "shares":149.5196871413,
    "weight":0.2012607055,
    "gross_market_value":265811.6142092093,
    "net_market_value":265811.6142092093,
    "name":"阿斯麦",
    "industry_labels":"半导体设备与材料",
    "market_value":265811.6142092093
  },
  {
    "date":1780963200000,
    "book":"long",
    "ticker":"US.AMAT",
    "shares":529.4579976262,
    "weight":0.2001243006,
    "gross_market_value":264310.726994955,
    "net_market_value":264310.726994955,
    "name":"应用材料",
    "industry_labels":"半导体设备与材料",
    "market_value":264310.726994955
  },
  {
    "date":1780963200000,
    "book":"long",
    "ticker":"US.KLAC",
    "shares":121.9253259309,
    "weight":0.1974989834,
    "gross_market_value":260843.3845368947,
    "net_market_value":260843.3845368947,
    "name":"科磊",
    "industry_labels":"半导体设备与材料",
    "market_value":260843.3845368947
  },
  {
    "date":1780963200000,
    "book":"long",
    "ticker":"US.CSCO",
    "shares":2155.1165549975,
    "weight":0.1963984156,
    "gross_market_value":259389.8285595038,
    "net_market_value":259389.8285595038,
    "name":"思科",
    "industry_labels":"通讯设备",
    "market_value":259389.8285595038
  }
]