{
  "summary": {
    "signal_date": "2026-04-24",
    "next_trade_date": null,
    "spy_above_ma100": true,
    "spy_adj_close": 713.94,
    "spy_ma100": 680.48369667672,
    "strategy_nav": 1.7986183543388266,
    "benchmark_nav": 1.0498148810914532,
    "data_dir": "/Users/richard/dowork/hk_gap_strategy/data/us_waterfall_dashboard_variants/er_3_8_20_100b",
    "warnings": [
      "Metadata file has no date column. Static metadata is used for all history; this may introduce point-in-time bias.",
      "Using static market_cap across history. This creates look-ahead bias risk for the $100.0B+ market-cap filter.",
      "Using static shares_outstanding across history. This approximates point-in-time market cap and may introduce bias."
    ],
    "config": {
      "start_date": "2026-01-01",
      "fast_window": 3,
      "mid_window": 8,
      "slow_window": 20,
      "initial_capital": 500000.0,
      "commission_per_order": 1.0,
      "min_market_cap": 100000000000.0,
      "market_filter_mode": "none",
      "mode": "mode_b",
      "selection_style": "waterfall",
      "rebalance_frequency": "daily",
      "industry_filter": "whitelist",
      "market": "US",
      "benchmark_label": "SPY",
      "market_cap_currency": "USD"
    },
    "variant": {
      "name": "ER 3/8/20 (100B)",
      "slug": "er_3_8_20_100b"
    },
    "current_holding_count": 10,
    "planned_holding_count": 10,
    "keep_count": 8,
    "buy_count": 2,
    "blocked_buy_count": 0,
    "allow_new_buys": true
  },
  "performance": {
    "CAGR": 5.662682905872098,
    "Annualized Return": 1.9692189687803543,
    "Annualized Volatility": 0.36609230508717033,
    "Sharpe Ratio": 5.379023108151544,
    "Sortino Ratio": 8.620516798123763,
    "Max Drawdown": -0.07455974650586605,
    "Calmar Ratio": 75.94825856102638,
    "Win Rate": 0.6153846153846154,
    "Monthly Win Rate": 1.0,
    "Turnover (Annualized)": 79.29334170840187,
    "Average Holding Count": 9.974358974358974,
    "Average Daily Turnover": 0.3146561178904836,
    "Beta vs SPY": 1.2474639697248175,
    "Alpha vs SPY": 1.7605397784363492,
    "Information Ratio vs SPY": 5.610283097355737
  },
  "paths": {
    "signal_top10_csv": "/Users/richard/dowork/hk_gap_strategy/results/daily_us_waterfall_dashboard/latest/er_3_8_20_100b/latest_signal_top10.csv",
    "planned_holdings_csv": "/Users/richard/dowork/hk_gap_strategy/results/daily_us_waterfall_dashboard/latest/er_3_8_20_100b/planned_holdings_top10.csv",
    "current_holdings_csv": "/Users/richard/dowork/hk_gap_strategy/results/daily_us_waterfall_dashboard/latest/er_3_8_20_100b/current_holdings.csv",
    "historical_buy_counts_csv": "/Users/richard/dowork/hk_gap_strategy/results/daily_us_waterfall_dashboard/latest/er_3_8_20_100b/historical_buy_counts.csv",
    "profit_contribution_csv": "/Users/richard/dowork/hk_gap_strategy/results/daily_us_waterfall_dashboard/latest/er_3_8_20_100b/profit_contribution_by_ticker.csv",
    "top10_profit_contributors_csv": "/Users/richard/dowork/hk_gap_strategy/results/daily_us_waterfall_dashboard/latest/er_3_8_20_100b/top10_profit_contributors.csv",
    "daily_nav_csv": "/Users/richard/dowork/hk_gap_strategy/results/daily_us_waterfall_dashboard/latest/er_3_8_20_100b/daily_nav.csv",
    "html": "/Users/richard/dowork/hk_gap_strategy/results/daily_us_waterfall_dashboard/latest/er_3_8_20_100b/index.html"
  }
}