[
  {
    "date":1784678400000,
    "book":"long",
    "ticker":"HK.03759",
    "shares":3646.6052959831,
    "weight":0.1160190764,
    "gross_market_value":86935.0702562362,
    "net_market_value":86935.0702562362,
    "name":"康龙化成",
    "industry_labels":null,
    "market_value":86935.0702562362
  },
  {
    "date":1784678400000,
    "book":"long",
    "ticker":"HK.02096",
    "shares":6011.4774075222,
    "weight":0.1068611487,
    "gross_market_value":80072.8790681951,
    "net_market_value":80072.8790681951,
    "name":"先声药业",
    "industry_labels":null,
    "market_value":80072.8790681951
  },
  {
    "date":1784678400000,
    "book":"long",
    "ticker":"HK.01548",
    "shares":4875.225894364,
    "weight":0.1016272485,
    "gross_market_value":76151.0284699654,
    "net_market_value":76151.0284699654,
    "name":"金斯瑞生物科技",
    "industry_labels":null,
    "market_value":76151.0284699654
  },
  {
    "date":1784678400000,
    "book":"long",
    "ticker":"HK.09969",
    "shares":5108.9358851792,
    "weight":0.0987264245,
    "gross_market_value":73977.3916173954,
    "net_market_value":73977.3916173954,
    "name":"诺诚健华",
    "industry_labels":null,
    "market_value":73977.3916173954
  },
  {
    "date":1784678400000,
    "book":"long",
    "ticker":"HK.02689",
    "shares":9330.393160754,
    "weight":0.097622607,
    "gross_market_value":73150.2823803117,
    "net_market_value":73150.2823803117,
    "name":"玖龙纸业",
    "industry_labels":null,
    "market_value":73150.2823803117
  },
  {
    "date":1784678400000,
    "book":"long",
    "ticker":"HK.00867",
    "shares":5958.3017846272,
    "weight":0.0973281141,
    "gross_market_value":72929.6138438365,
    "net_market_value":72929.6138438365,
    "name":"康哲药业",
    "industry_labels":null,
    "market_value":72929.6138438365
  },
  {
    "date":1784678400000,
    "book":"long",
    "ticker":"HK.06990",
    "shares":140.8219459117,
    "weight":0.0971617389,
    "gross_market_value":72804.9460363586,
    "net_market_value":72804.9460363586,
    "name":"科伦博泰生物-B",
    "industry_labels":null,
    "market_value":72804.9460363586
  },
  {
    "date":1784678400000,
    "book":"long",
    "ticker":"HK.02269",
    "shares":1861.7758563393,
    "weight":0.0965030433,
    "gross_market_value":72311.3742602202,
    "net_market_value":72311.3742602202,
    "name":"药明生物",
    "industry_labels":null,
    "market_value":72311.3742602202
  },
  {
    "date":1784678400000,
    "book":"long",
    "ticker":"HK.01093",
    "shares":8432.7494669488,
    "weight":0.0945328776,
    "gross_market_value":70835.0955223699,
    "net_market_value":70835.0955223699,
    "name":"石药集团",
    "industry_labels":null,
    "market_value":70835.0955223699
  },
  {
    "date":1784678400000,
    "book":"long",
    "ticker":"HK.03888",
    "shares":2863.4139267378,
    "weight":0.0938527256,
    "gross_market_value":70325.4460406808,
    "net_market_value":70325.4460406808,
    "name":"金山软件",
    "industry_labels":null,
    "market_value":70325.4460406808
  },
  {
    "date":1784678400000,
    "book":"spy_hedge",
    "ticker":"恒生指数",
    "shares":7.4912099309,
    "weight":-0.2488614741,
    "gross_market_value":186476.1417981272,
    "net_market_value":-186476.1417981272,
    "name":"恒生指数 动态对冲",
    "industry_labels":"Hedge",
    "market_value":-186476.1417981272
  }
]