[
  {
    "signal_date":1778457600000,
    "ticker":"HK.00290",
    "er8":0.4152964747,
    "er15":0.4495435191,
    "er40":1.3827834468,
    "adv20":144828771.650000006,
    "adj_close":9.6,
    "market_cap_used":39978948142.3199996948,
    "vol20_ann":0.9987029307,
    "up_day_ratio20":0.7,
    "er_consistency_penalty":0.9674869721,
    "er20_vol_score":1.3845793422,
    "book":"long",
    "stage":"top10",
    "rank":1,
    "trade_date":null,
    "spy_ma":25976.3011,
    "spy_above_ma":true,
    "allow_new_buys":true,
    "market_filter_mode":"configured_price_above_ma",
    "selection_style":"dual_objective_liquidity",
    "spy_vol_ann":0.1654276474,
    "high_vol_regime":false,
    "target_count_cap":10,
    "name":"国富量子",
    "industry_labels":null,
    "spy_adj_close":26406.84,
    "spy_ma100":26118.7865,
    "action":"keep",
    "planned_holding":true
  },
  {
    "signal_date":1778457600000,
    "ticker":"HK.06809",
    "er8":0.5525031621,
    "er15":0.9896218439,
    "er40":1.2590205322,
    "adv20":859955977.4900000095,
    "adj_close":418.6,
    "market_cap_used":230629143962.700012207,
    "vol20_ann":0.9677057619,
    "up_day_ratio20":0.7,
    "er_consistency_penalty":0.70651737,
    "er20_vol_score":1.3010365151,
    "book":"long",
    "stage":"top10",
    "rank":2,
    "trade_date":null,
    "spy_ma":25976.3011,
    "spy_above_ma":true,
    "allow_new_buys":true,
    "market_filter_mode":"configured_price_above_ma",
    "selection_style":"dual_objective_liquidity",
    "spy_vol_ann":0.1654276474,
    "high_vol_regime":false,
    "target_count_cap":10,
    "name":"澜起科技",
    "industry_labels":null,
    "spy_adj_close":26406.84,
    "spy_ma100":26118.7865,
    "action":"keep",
    "planned_holding":true
  },
  {
    "signal_date":1778457600000,
    "ticker":"HK.01888",
    "er8":0.2058255768,
    "er15":0.5461325093,
    "er40":0.9227657945,
    "adv20":1414384736.3779997826,
    "adj_close":43.96,
    "market_cap_used":64399575500.0,
    "vol20_ann":0.7594893037,
    "up_day_ratio20":0.8,
    "er_consistency_penalty":0.7169402177,
    "er20_vol_score":1.2149819491,
    "book":"long",
    "stage":"top10",
    "rank":3,
    "trade_date":null,
    "spy_ma":25976.3011,
    "spy_above_ma":true,
    "allow_new_buys":true,
    "market_filter_mode":"configured_price_above_ma",
    "selection_style":"dual_objective_liquidity",
    "spy_vol_ann":0.1654276474,
    "high_vol_regime":false,
    "target_count_cap":10,
    "name":"建滔积层板",
    "industry_labels":null,
    "spy_adj_close":26406.84,
    "spy_ma100":26118.7865,
    "action":"keep",
    "planned_holding":true
  },
  {
    "signal_date":1778457600000,
    "ticker":"HK.06166",
    "er8":0.2810399701,
    "er15":0.1762447062,
    "er40":0.7508465919,
    "adv20":1740177292.4349999428,
    "adj_close":145.6,
    "market_cap_used":26695633236.0999984741,
    "vol20_ann":1.9044183672,
    "up_day_ratio20":0.6,
    "er_consistency_penalty":0.6793971497,
    "er20_vol_score":0.3942655694,
    "book":"long",
    "stage":"top10",
    "rank":4,
    "trade_date":null,
    "spy_ma":25976.3011,
    "spy_above_ma":true,
    "allow_new_buys":true,
    "market_filter_mode":"configured_price_above_ma",
    "selection_style":"dual_objective_liquidity",
    "spy_vol_ann":0.1654276474,
    "high_vol_regime":false,
    "target_count_cap":10,
    "name":"剑桥科技",
    "industry_labels":null,
    "spy_adj_close":26406.84,
    "spy_ma100":26118.7865,
    "action":"keep",
    "planned_holding":true
  },
  {
    "signal_date":1778457600000,
    "ticker":"HK.06088",
    "er8":0.2423060089,
    "er15":0.233956525,
    "er40":0.7005534816,
    "adv20":570662212.7885000706,
    "adj_close":9.86,
    "market_cap_used":51126170004.0,
    "vol20_ann":0.870004839,
    "up_day_ratio20":0.65,
    "er_consistency_penalty":0.4749464405,
    "er20_vol_score":0.8052294082,
    "book":"long",
    "stage":"top10",
    "rank":5,
    "trade_date":null,
    "spy_ma":25976.3011,
    "spy_above_ma":true,
    "allow_new_buys":true,
    "market_filter_mode":"configured_price_above_ma",
    "selection_style":"dual_objective_liquidity",
    "spy_vol_ann":0.1654276474,
    "high_vol_regime":false,
    "target_count_cap":10,
    "name":"FIT HON TENG",
    "industry_labels":null,
    "spy_adj_close":26406.84,
    "spy_ma100":26118.7865,
    "action":"keep",
    "planned_holding":true
  },
  {
    "signal_date":1778457600000,
    "ticker":"HK.02631",
    "er8":0.3839681539,
    "er15":0.3939050044,
    "er40":0.6016134285,
    "adv20":304377265.1599999666,
    "adj_close":88.55,
    "market_cap_used":23882001848.3199996948,
    "vol20_ann":1.1022722707,
    "up_day_ratio20":0.5,
    "er_consistency_penalty":0.2176452746,
    "er20_vol_score":0.5457938519,
    "book":"long",
    "stage":"top10",
    "rank":6,
    "trade_date":null,
    "spy_ma":25976.3011,
    "spy_above_ma":true,
    "allow_new_buys":true,
    "market_filter_mode":"configured_price_above_ma",
    "selection_style":"dual_objective_liquidity",
    "spy_vol_ann":0.1654276474,
    "high_vol_regime":false,
    "target_count_cap":10,
    "name":"天岳先进",
    "industry_labels":null,
    "spy_adj_close":26406.84,
    "spy_ma100":26118.7865,
    "action":"buy",
    "planned_holding":true
  },
  {
    "signal_date":1778457600000,
    "ticker":"HK.01347",
    "er8":0.1543882465,
    "er15":0.4712399372,
    "er40":0.4609963536,
    "adv20":3582133197.302500248,
    "adj_close":134.0,
    "market_cap_used":153606685861.200012207,
    "vol20_ann":0.884687303,
    "up_day_ratio20":0.65,
    "er_consistency_penalty":0.3270952742,
    "er20_vol_score":0.5210839491,
    "book":"long",
    "stage":"top10",
    "rank":7,
    "trade_date":null,
    "spy_ma":25976.3011,
    "spy_above_ma":true,
    "allow_new_buys":true,
    "market_filter_mode":"configured_price_above_ma",
    "selection_style":"dual_objective_liquidity",
    "spy_vol_ann":0.1654276474,
    "high_vol_regime":false,
    "target_count_cap":10,
    "name":"华虹半导体",
    "industry_labels":null,
    "spy_adj_close":26406.84,
    "spy_ma100":26118.7865,
    "action":"keep",
    "planned_holding":true
  },
  {
    "signal_date":1778457600000,
    "ticker":"HK.06869",
    "er8":0.1164359076,
    "er15":0.2498002547,
    "er40":0.4499780169,
    "adv20":4264512323.1900000572,
    "adj_close":259.4,
    "market_cap_used":127331805610.3999938965,
    "vol20_ann":1.1500618146,
    "up_day_ratio20":0.55,
    "er_consistency_penalty":0.3335421093,
    "er20_vol_score":0.3912642009,
    "book":"long",
    "stage":"top10",
    "rank":8,
    "trade_date":null,
    "spy_ma":25976.3011,
    "spy_above_ma":true,
    "allow_new_buys":true,
    "market_filter_mode":"configured_price_above_ma",
    "selection_style":"dual_objective_liquidity",
    "spy_vol_ann":0.1654276474,
    "high_vol_regime":false,
    "target_count_cap":10,
    "name":"长飞光纤光缆",
    "industry_labels":null,
    "spy_adj_close":26406.84,
    "spy_ma100":26118.7865,
    "action":"keep",
    "planned_holding":true
  },
  {
    "signal_date":1778457600000,
    "ticker":"HK.00148",
    "er8":0.1905874958,
    "er15":0.3468178474,
    "er40":0.4448253316,
    "adv20":641368637.809499979,
    "adj_close":55.85,
    "market_cap_used":41029700466.7200012207,
    "vol20_ann":0.5967731034,
    "up_day_ratio20":0.65,
    "er_consistency_penalty":0.2542378358,
    "er20_vol_score":0.7453843496,
    "book":"long",
    "stage":"top10",
    "rank":9,
    "trade_date":null,
    "spy_ma":25976.3011,
    "spy_above_ma":true,
    "allow_new_buys":true,
    "market_filter_mode":"configured_price_above_ma",
    "selection_style":"dual_objective_liquidity",
    "spy_vol_ann":0.1654276474,
    "high_vol_regime":false,
    "target_count_cap":10,
    "name":"建滔集团",
    "industry_labels":null,
    "spy_adj_close":26406.84,
    "spy_ma100":26118.7865,
    "action":"keep",
    "planned_holding":true
  },
  {
    "signal_date":1778457600000,
    "ticker":"HK.01729",
    "er8":0.1072014708,
    "er15":0.1455199195,
    "er40":0.4309360094,
    "adv20":309971171.8035000563,
    "adj_close":24.3,
    "market_cap_used":32992155281.0800018311,
    "vol20_ann":0.7146648329,
    "up_day_ratio20":0.6,
    "er_consistency_penalty":0.3237345385,
    "er20_vol_score":0.6029903663,
    "book":"long",
    "stage":"top10",
    "rank":10,
    "trade_date":null,
    "spy_ma":25976.3011,
    "spy_above_ma":true,
    "allow_new_buys":true,
    "market_filter_mode":"configured_price_above_ma",
    "selection_style":"dual_objective_liquidity",
    "spy_vol_ann":0.1654276474,
    "high_vol_regime":false,
    "target_count_cap":10,
    "name":"汇聚科技",
    "industry_labels":null,
    "spy_adj_close":26406.84,
    "spy_ma100":26118.7865,
    "action":"buy",
    "planned_holding":true
  }
]