[
  {
    "date":1782432000000,
    "book":"long",
    "ticker":"US.KLAC",
    "shares":1351.1924527357,
    "weight":0.2137111728,
    "gross_market_value":335960.4914481957,
    "net_market_value":335960.4914481957,
    "name":"科磊",
    "industry_labels":"半导体设备与材料",
    "market_value":335960.4914481957
  },
  {
    "date":1782432000000,
    "book":"long",
    "ticker":"US.GE",
    "shares":906.7776448888,
    "weight":0.212846342,
    "gross_market_value":334600.9509639756,
    "net_market_value":334600.9509639756,
    "name":"GE航天航空",
    "industry_labels":"航空航天与国防",
    "market_value":334600.9509639756
  },
  {
    "date":1782432000000,
    "book":"long",
    "ticker":"US.MU",
    "shares":290.2341888589,
    "weight":0.2090550213,
    "gross_market_value":328640.8790705444,
    "net_market_value":328640.8790705444,
    "name":"美光科技",
    "industry_labels":"半导体",
    "market_value":328640.8790705444
  },
  {
    "date":1782432000000,
    "book":"long",
    "ticker":"US.DELL",
    "shares":744.7209793767,
    "weight":0.1892511472,
    "gross_market_value":297508.5840512107,
    "net_market_value":297508.5840512107,
    "name":"戴尔科技",
    "industry_labels":"计算机硬件",
    "market_value":297508.5840512107
  },
  {
    "date":1782432000000,
    "book":"long",
    "ticker":"US.CSCO",
    "shares":2388.3284310657,
    "weight":0.1728465942,
    "gross_market_value":271720.1256023429,
    "net_market_value":271720.1256023429,
    "name":"思科",
    "industry_labels":"通讯设备",
    "market_value":271720.1256023429
  }
]